eth_testrpc-1.3.5.dist-info/METADATA
eth_testrpc-1.3.5.dist-info/RECORD
eth_testrpc-1.3.5.dist-info/WHEEL
eth_testrpc-1.3.5.dist-info/entry_points.txt
eth_testrpc-1.3.5.dist-info/top_level.txt
testrpc/__init__.py
testrpc/cli.py
testrpc/rpc.py
testrpc/server.py
testrpc/utils.py
testrpc/client/__init__.py
testrpc/client/client.py
testrpc/client/filters.py
testrpc/client/serializers.py
testrpc/client/utils.py
testrpc/compat/__init__.py
testrpc/compat/compat_gevent.py
testrpc/compat/compat_stdlib.py
