Metadata-Version: 2.1
Name: eth-testrpc
Version: 1.3.5
Summary: An Ethereum simulator for aiding smart contract development.
Home-page: https://github.com/pipermerriam/eth-testrpc
Author: Piper Merriam
Author-email: pipermerriam@gmail.com
License: MIT
Keywords: ethereum blockchain development testing
Platform: UNKNOWN
Classifier: Intended Audience :: Developers
Classifier: Topic :: Software Development :: Testing
Classifier: License :: OSI Approved :: MIT License
Classifier: Programming Language :: Python :: 2
Classifier: Programming Language :: Python :: 2.7
Classifier: Programming Language :: Python :: 3
Classifier: Programming Language :: Python :: 3.4
Classifier: Programming Language :: Python :: 3.5
Provides-Extra: gevent
